pthbz/__init__.py
pthbz/async_client.py
pthbz/cli.py
pthbz/client.py
pthbz/exceptions.py
pthbz/models.py
pthbz/py.typed
pthbz/utils.py
pthbz/validators.py
pthbz-1.0.4.dist-info/licenses/LICENSE
pthbz-1.0.4.dist-info/METADATA
pthbz-1.0.4.dist-info/WHEEL
pthbz-1.0.4.dist-info/entry_points.txt
pthbz-1.0.4.dist-info/top_level.txt
pthbz-1.0.4.dist-info/RECORD
