Metadata-Version: 2.4
Name: pthbz
Version: 1.0.4
Summary: Python SDK and CLI for creating short links with permanent 301 redirects, interstitial (anti-bot) redirects, and on-demand QR codes via pth.bz.
Author: Avel Kox
License-Expression: MIT
Project-URL: Homepage, https://pth.bz/
Project-URL: Documentation, https://pth.bz/docs
Project-URL: Source, https://github.com/pthbz/pthbz-python
Project-URL: Issues, https://github.com/pthbz/pthbz-python/issues
Keywords: url shortener,link shortener,short link,short urls,301 redirect,permanent redirect,interstitial,anti-bot,referrer hiding,privacy,no tracking,utm,campaign tracking,marketing links,seo redirects,qr,qr code,qr generator,python sdk,http client,requests,httpx,asyncio,cli,tiny links,branded links,biolink,social links,pth.bz
Classifier: Development Status :: 5 - Production/Stable
Classifier: Environment :: Console
Classifier: Intended Audience :: Developers
Classifier: Operating System :: OS Independent
Classifier: Programming Language :: Python
Classifier: Programming Language :: Python :: 3
Classifier: Programming Language :: Python :: 3 :: Only
Classifier: Programming Language :: Python :: 3.8
Classifier: Programming Language :: Python :: 3.9
Classifier: Programming Language :: Python :: 3.10
Classifier: Programming Language :: Python :: 3.11
Classifier: Programming Language :: Python :: 3.12
Classifier: Topic :: Internet :: WWW/HTTP
Classifier: Topic :: Software Development :: Libraries :: Python Modules
Classifier: Framework :: AsyncIO
Classifier: Typing :: Typed
Requires-Python: >=3.8
License-File: LICENSE
Requires-Dist: requests>=2.31.0
Requires-Dist: httpx>=0.27.0
Requires-Dist: idna>=3.6
Dynamic: license-file
